clode/BUILD
clode/__init__.py
clode/features.py
clode/function_converter.py
clode/opencl_builtins.py
clode/py.typed
clode/runtime.py
clode/solver.py
clode/trajectory.py
clode/xpp_parser.py
clode/cpp/BUILD
clode/cpp/CLODE.cpp
clode/cpp/CLODE.hpp
clode/cpp/CLODEfeatures.cpp
clode/cpp/CLODEfeatures.hpp
clode/cpp/CLODEpython.cpp
clode/cpp/CLODEtrajectory.cpp
clode/cpp/CLODEtrajectory.hpp
clode/cpp/OpenCLResource.cpp
clode/cpp/OpenCLResource.hpp
clode/cpp/__init__.py
clode/cpp/clODE_random.cl
clode/cpp/clODE_struct_defs.cl
clode/cpp/clODE_utilities.cl
clode/cpp/clode_cpp_wrapper.cpython-312-darwin.so
clode/cpp/clode_cpp_wrapper.pyi
clode/cpp/features.cl
clode/cpp/initializeObserver.cl
clode/cpp/observers.cl
clode/cpp/odedriver.cl
clode/cpp/realtype.cl
clode/cpp/steppers.cl
clode/cpp/trajectory.cl
clode/cpp/transient.cl
clode/cpp/OpenCL/BUILD
clode/cpp/OpenCL/cl.hpp
clode/cpp/OpenCL/cl2.hpp
clode/cpp/OpenCL/opencl.hpp
clode/cpp/logging/BUILD
clode/cpp/logging/MatlabSink.hpp
clode/cpp/logging/PythonSink.hpp
clode/cpp/observers/BUILD
clode/cpp/observers/observer_basic.clh
clode/cpp/observers/observer_basic_allVar.clh
clode/cpp/observers/observer_local_maximum.clh
clode/cpp/observers/observer_neighborhood_1.clh
clode/cpp/observers/observer_neighborhood_2.clh
clode/cpp/observers/observer_template.clh
clode/cpp/observers/observer_threshold_1.clh
clode/cpp/observers/observer_threshold_2.clh
clode/cpp/steppers/BUILD
clode/cpp/steppers/adaptive_bs23.clh
clode/cpp/steppers/adaptive_dp45.clh
clode/cpp/steppers/adaptive_explicit_step.clh
clode/cpp/steppers/adaptive_he12.clh
clode/cpp/steppers/adaptive_rkck.clh
clode/cpp/steppers/fixed_explicit_Euler.clh
clode/cpp/steppers/fixed_explicit_RK4.clh
clode/cpp/steppers/fixed_explicit_Trapezoidal.clh
clode/cpp/steppers/fixed_explicit_step.clh
clode/cpp/steppers/fixed_explicit_stochastic_Euler.clh
clode-0.9.0.dist-info/METADATA
clode-0.9.0.dist-info/WHEEL
clode-0.9.0.dist-info/top_level.txt
clode-0.9.0.dist-info/RECORD
