Metadata-Version: 2.1
Name: clode
Version: 0.9.0
Summary: A Python package for solving ordinary differential equations on the GPU using OpenCL
Author-email: Patrick Fletcher <patrick.allen.fletcher@gmail.com>
Maintainer-email: Patrick Fletcher <patrick.allen.fletcher@gmail.com>, Wolf Byttner <wolf@byttner.org>
Project-URL: Documentation, https://patrickfletcher.github.io/clODE/
Project-URL: Repository, https://github.com/patrickfletcher/clODE
Classifier: Development Status :: 3 - Alpha
Classifier: Intended Audience :: Science/Research
Classifier: License :: OSI Approved :: MIT License
Classifier: Operating System :: MacOS :: MacOS X
Classifier: Operating System :: Microsoft :: Windows
Classifier: Operating System :: POSIX
Classifier: Environment :: GPU
Classifier: Programming Language :: Python :: 3
Classifier: Programming Language :: Python :: 3.8
Classifier: Programming Language :: Python :: 3.9
Classifier: Programming Language :: Python :: 3.10
Classifier: Programming Language :: Python :: 3.11
Classifier: Programming Language :: Python :: 3.12
Classifier: Programming Language :: C++
Classifier: Topic :: Scientific/Engineering
Classifier: Topic :: Scientific/Engineering :: Mathematics
Classifier: Topic :: Scientific/Engineering :: Physics
Classifier: Topic :: Software Development :: Libraries
Requires-Python: >=3.8
